{"NPCs":[{"Nimi":"test","Nakoetaisyys":15,"Vari":{},"Merkki":"T","X":57,"Y":34,"Napparyys":0,"Voimakkuus":0,"Puolustus":0,"Elama":0,"Inventaario":null}],"Vastustajat":[{"Nimi":"enemy","Nakoetaisyys":15,"Vari":{},"Merkki":"E","X":63,"Y":36,"Napparyys":1,"Voimakkuus":1,"Puolustus":1,"Elama":5,"Inventaario":[]}],"Ovet":[{"Vari":{},"Merkki":"|","X":60,"Y":20}],"Esineet":[{"Nimi":"Coin","Merkki":"o","Vari":{},"Maara":1,"X":57,"Y":29},{"Nimi":"Woolen hood","Merkki":"n","Vari":{},"Maara":1,"X":63,"Y":25},{"Nimi":"Loaf of bread","Merkki":"b","Vari":{},"Maara":1,"X":65,"Y":27},{"Nimi":"Moon Mushroom","Merkki":"t","Vari":{},"Maara":2,"X":67,"Y":42},{"Nimi":"Bow","Merkki":")","Vari":{},"Maara":1,"X":55,"Y":24},{"Nimi":"Arrow","Merkki":"I","Vari":{},"Maara":1,"X":58,"Y":22}],"Solut":[{"Vari":{},"Taustavari":{},"Merkki":".","X":49,"Y":21,"IsTransparent":false,"IsWalkable":false,"IsInFov":true,"IsExplored":false},{"Vari":{},"Taustavari":{},"Merkki":".","X":50,"Y":21,"IsTransparent":false,"IsWalkable":false,"IsInFov":true,"IsExplored":false},{"Vari":{},"Taustavari":{},"Merkki":".","X":51,"Y":21,"IsTransparent":false,"IsWalkable":false,"IsInFov":true,"IsExplored":false},{"Vari":{},"Taustavari":{},"Merkki":".","X":52,"Y":21,"IsTransparent":false,"IsWalkable":false,"IsInFov":true,"IsExplored":false},{"Vari":{},"Taustavari":{},"Merkki":".","X":53,"Y":21,"IsTransparent":false,"IsWalkable":false,"IsInFov":true,"IsExplored":false},{"Vari":{},"Taustavari":{},"Merkki":".","X":54,"Y":21,"IsTransparent":false,"IsWalkable":false,"IsInFov":true,"IsExplored":false},{"Vari":{},"Taustavari":{},"Merkki":".","X":55,"Y":21,"IsTransparent":false,"IsWalkable":false,"IsInFov":true,"IsExplored":false},{"Vari":{},"Taustavari":{},"Merkki":".","X":56,"Y":21,"IsTransparent":false,"IsWalkable":false,"IsInFov":true,"IsExplored":false},{"Vari":{},"Taustavari":{},"Merkki":".","X":57,"Y":21,"IsTransparent":false,"IsWalkable":false,"IsInFov":true,"IsExplored":false},{"Vari":{},"Taustavari":{},"Merkki":".","X":58,"Y":21,"IsTransparent":false,"IsWalkable":false,"IsInFov":true,"IsExplored":false},{"Vari":{},"Taustavari":{},"Merkki":".","X":59,"Y":21,"IsTransparent":false,"IsWalkable":false,"IsInFov":true,"IsExplored":false},{"Vari":{},"Taustavari":{},"Merkki":".","X":60,"Y":21,"IsTransparent":false,"IsWalkable":false,"IsInFov":true,"IsExplored":false},{"Vari":{},"Taustavari":{},"Merkki":".","X":61,"Y":21,"IsTransparent":false,"IsWalkable":false,"IsInFov":true,"IsExplored":false},{"Vari":{},"Taustavari":{},"Merkki":".","X":62,"Y":21,"IsTransparent":false,"IsWalkable":false,"IsInFov":true,"IsExplored":false},{"Vari":{},"Taustavari":{},"Merkki":".","X":63,"Y":21,"IsTransparent":false,"IsWalkable":false,"IsInFov":true,"IsExplored":false},{"Vari":{},"Taustavari":{},"Merkki":".","X":64,"Y":21,"IsTransparent":false,"IsWalkable":false,"IsInFov":true,"IsExplored":false},{"Vari":{},"Taustavari":{},"Merkki":".","X":65,"Y":21,"IsTransparent":false,"IsWalkable":false,"IsInFov":true,"IsExplored":false},{"Vari":{},"Taustavari":{},"Merkki":".","X":66,"Y":21,"IsTransparent":false,"IsWalkable":false,"IsInFov":true,"IsExplored":false},{"Vari":{},"Taustavari":{},"Merkki":".","X":67,"Y":21,"IsTransparent":false,"IsWalkable":false,"IsInFov":true,"IsExplored":false},{"Vari":{},"Taustavari":{},"Merkki":".","X":68,"Y":21,"IsTransparent":false,"IsWalkable":false,"IsInFov":true,"IsExplored":false},{"Vari":{},"Taustavari":{},"Merkki":".","X":69,"Y":21,"IsTransparent":false,"IsWalkable":false,"IsInFov":true,"IsExplored":false},{"Vari":{},"Taustavari":{},"Merkki":".","X":70,"Y":21,"IsTransparent":false,"IsWalkable":false,"IsInFov":true,"IsExplored":false},{"Vari":{},"Taustavari":{},"Merkki":".","X":71,"Y":21,"IsTransparent":false,"IsWalkable":false,"IsInFov":true,"IsExplored":false},{"Vari":{},"Taustavari":{},"Merkki":".","X":49,"Y":22,"IsTransparent":false,"IsWalkable":false,"IsInFov":true,"IsExplored":false},{"Vari":{},"Taustavari":{},"Merkki":".","X":50,"Y":22,"IsTransparent":false,"IsWalkable":false,"IsInFov":true,"IsExplored":false},{"Vari":{},"Taustavari":{},"Merkki":".","X":51,"Y":22,"IsTransparent":false,"IsWalkable":false,"IsInFov":true,"IsExplored":false},{"Vari":{},"Taustavari":{},"Merkki":".","X":52,"Y":22,"IsTransparent":false,"IsWalkable":false,"IsInFov":true,"IsExplored":false},{"Vari":{},"Taustavari":{},"Merkki":".","X":53,"Y":22,"IsTransparent":false,"IsWalkable":false,"IsInFov":true,"IsExplored":false},{"Vari":{},"Taustavari":{},"Merkki":".","X":54,"Y":22,"IsTransparent":false,"IsWalkable":false,"IsInFov":true,"IsExplored":false},{"Vari":{},"Taustavari":{},"Merkki":".","X":55,"Y":22,"IsTransparent":false,"IsWalkable":false,"IsInFov":true,"IsExplored":false},{"Vari":{},"Taustavari":{},"Merkki":".","X":56,"Y":22,"IsTransparent":false,"IsWalkable":false,"IsInFov":true,"IsExplored":false},{"Vari":{},"Taustavari":{},"Merkki":".","X":57,"Y":22,"IsTransparent":false,"IsWalkable":false,"IsInFov":true,"IsExplored":false},{"Vari":{},"Taustavari":{},"Merkki":".","X":58,"Y":22,"IsTransparent":false,"IsWalkable":false,"IsInFov":true,"IsExplored":false},{"Vari":{},"Taustavari":{},"Merkki":".","X":59,"Y":22,"IsTransparent":false,"IsWalkable":false,"IsInFov":true,"IsExplored":false},{"Vari":{},"Taustavari":{},"Merkki":".","X":60,"Y":22,"IsTransparent":false,"IsWalkable":false,"IsInFov":true,"IsExplored":false},{"Vari":{},"Taustavari":{},"Merkki":".","X":61,"Y":22,"IsTransparent":false,"IsWalkable":false,"IsInFov":true,"IsExplored":false},{"Vari":{},"Taustavari":{},"Merkki":".","X":62,"Y":22,"IsTransparent":false,"IsWalkable":false,"IsInFov":true,"IsExplored":false},{"Vari":{},"Taustavari":{},"Merkki":".","X":63,"Y":22,"IsTransparent":false,"IsWalkable":false,"IsInFov":true,"IsExplored":false},{"Vari":{},"Taustavari":{},"Merkki":".","X":64,"Y":22,"IsTransparent":false,"IsWalkable":false,"IsInFov":true,"IsExplored":false},{"Vari":{},"Taustavari":{},"Merkki":".","X":65,"Y":22,"IsTransparent":false,"IsWalkable":false,"IsInFov":true,"IsExplored":false},{"Vari":{},"Taustavari":{},"Merkki":".","X":66,"Y":22,"IsTransparent":false,"IsWalkable":false,"IsInFov":true,"IsExplored":false},{"Vari":{},"Taustavari":{},"Merkki":".","X":67,"Y":22,"IsTransparent":false,"IsWalkable":false,"IsInFov":true,"IsExplored":false},{"Vari":{},"Taustavari":{},"Merkki":".","X":68,"Y":22,"IsTransparent":false,"IsWalkable":false,"IsInFov":true,"IsExplored":false},{"Vari":{},"Taustavari":{},"Merkki":".","X":69,"Y":22,"IsTransparent":false,"IsWalkable":false,"IsInFov":true,"IsExplored":false},{"Vari":{},"Taustavari":{},"Merkki":".","X":70,"Y":22,"IsTransparent":false,"IsWalkable":false,"IsInFov":true,"IsExplored":false},{"Vari":{},"Taustavari":{},"Merkki":".","X":71,"Y":22,"IsTransparent":false,"IsWalkable":false,"IsInFov":true,"IsExplored":false},{"Vari":{},"Taustavari":{},"Merkki":".","X":49,"Y":23,"IsTransparent":false,"IsWalkable":false,"IsInFov":true,"IsExplored":false},{"Vari":{},"Taustavari":{},"Merkki":".","X":50,"Y":23,"IsTransparent":false,"IsWalkable":false,"IsInFov":true,"IsExplored":false},{"Vari":{},"Taustavari":{},"Merkki":".","X":51,"Y":23,"IsTransparent":false,"IsWalkable":false,"IsInFov":true,"IsExplored":false},{"Vari":{},"Taustavari":{},"Merkki":".","X":52,"Y":23,"IsTransparent":false,"IsWalkable":false,"IsInFov":true,"IsExplored":false},{"Vari":{},"Taustavari":{},"Merkki":".","X":53,"Y":23,"IsTransparent":false,"IsWalkable":false,"IsInFov":true,"IsExplored":false},{"Vari":{},"Taustavari":{},"Merkki":".","X":54,"Y":23,"IsTransparent":false,"IsWalkable":false,"IsInFov":true,"IsExplored":false},{"Vari":{},"Taustavari":{},"Merkki":".","X":55,"Y":23,"IsTransparent":false,"IsWalkable":false,"IsInFov":true,"IsExplored":false},{"Vari":{},"Taustavari":{},"Merkki":".","X":56,"Y":23,"IsTransparent":false,"IsWalkable":false,"IsInFov":true,"IsExplored":false},{"Vari":{},"Taustavari":{},"Merkki":".","X":57,"Y":23,"IsTransparent":false,"IsWalkable":false,"IsInFov":true,"IsExplored":false},{"Vari":{},"Taustavari":{},"Merkki":".","X":58,"Y":23,"IsTransparent":false,"IsWalkable":false,"IsInFov":true,"IsExplored":false},{"Vari":{},"Taustavari":{},"Merkki":".","X":59,"Y":23,"IsTransparent":false,"IsWalkable":false,"IsInFov":true,"IsExplored":false},{"Vari":{},"Taustavari":{},"Merkki":".","X":60,"Y":23,"IsTransparent":false,"IsWalkable":false,"IsInFov":true,"IsExplored":false},{"Vari":{},"Taustavari":{},"Merkki":".","X":61,"Y":23,"IsTransparent":false,"IsWalkable":false,"IsInFov":true,"IsExplored":false},{"Vari":{},"Taustavari":{},"Merkki":".","X":62,"Y":23,"IsTransparent":false,"IsWalkable":false,"IsInFov":true,"IsExplored":false},{"Vari":{},"Taustavari":{},"Merkki":".","X":63,"Y":23,"IsTransparent":false,"IsWalkable":false,"IsInFov":true,"IsExplored":false},{"Vari":{},"Taustavari":{},"Merkki":".","X":64,"Y":23,"IsTransparent":false,"IsWalkable":false,"IsInFov":true,"IsExplored":false},{"Vari":{},"Taustavari":{},"Merkki":".","X":65,"Y":23,"IsTransparent":false,"IsWalkable":false,"IsInFov":true,"IsExplored":false},{"Vari":{},"Taustavari":{},"Merkki":".","X":66,"Y":23,"IsTransparent":false,"IsWalkable":false,"IsInFov":true,"IsExplored":false},{"Vari":{},"Taustavari":{},"Merkki":".","X":67,"Y":23,"IsTransparent":false,"IsWalkable":false,"IsInFov":true,"IsExplored":false},{"Vari":{},"Taustavari":{},"Merkki":".","X":68,"Y":23,"IsTransparent":false,"IsWalkable":false,"IsInFov":true,"IsExplored":false},{"Vari":{},"Taustavari":{},"Merkki":".","X":69,"Y":23,"IsTransparent":false,"IsWalkable":false,"IsInFov":true,"IsExplored":false},{"Vari":{},"Taustavari":{},"Merkki":".","X":70,"Y":23,"IsTransparent":false,"IsWalkable":false,"IsInFov":true,"IsExplored":false},{"Vari":{},"Taustavari":{},"Merkki":".","X":71,"Y":23,"IsTransparent":false,"IsWalkable":false,"IsInFov":true,"IsExplored":false},{"Vari":{},"Taustavari":{},"Merkki":".","X":49,"Y":24,"IsTransparent":false,"IsWalkable":false,"IsInFov":true,"IsExplored":false},{"Vari":{},"Taustavari":{},"Merkki":".","X":50,"Y":24,"IsTransparent":false,"IsWalkable":false,"IsInFov":true,"IsExplored":false},{"Vari":{},"Taustavari":{},"Merkki":".","X":51,"Y":24,"IsTransparent":false,"IsWalkable":false,"IsInFov":true,"IsExplored":false},{"Vari":{},"Taustavari":{},"Merkki":".","X":52,"Y":24,"IsTransparent":false,"IsWalkable":false,"IsInFov":true,"IsExplored":false},{"Vari":{},"Taustavari":{},"Merkki":".","X":53,"Y":24,"IsTransparent":false,"IsWalkable":false,"IsInFov":true,"IsExplored":false},{"Vari":{},"Taustavari":{},"Merkki":".","X":54,"Y":24,"IsTransparent":false,"IsWalkable":false,"IsInFov":true,"IsExplored":false},{"Vari":{},"Taustavari":{},"Merkki":".","X":55,"Y":24,"IsTransparent":false,"IsWalkable":false,"IsInFov":true,"IsExplored":false},{"Vari":{},"Taustavari":{},"Merkki":".","X":56,"Y":24,"IsTransparent":false,"IsWalkable":false,"IsInFov":true,"IsExplored":false},{"Vari":{},"Taustavari":{},"Merkki":".","X":57,"Y":24,"IsTransparent":false,"IsWalkable":false,"IsInFov":true,"IsExplored":false},{"Vari":{},"Taustavari":{},"Merkki":".","X":58,"Y":24,"IsTransparent":false,"IsWalkable":false,"IsInFov":true,"IsExplored":false},{"Vari":{},"Taustavari":{},"Merkki":".","X":59,"Y":24,"IsTransparent":false,"IsWalkable":false,"IsInFov":true,"IsExplored":false},{"Vari":{},"Taustavari":{},"Merkki":".","X":60,"Y":24,"IsTransparent":false,"IsWalkable":false,"IsInFov":true,"IsExplored":false},{"Vari":{},"Taustavari":{},"Merkki":".","X":61,"Y":24,"IsTransparent":false,"IsWalkable":false,"IsInFov":true,"IsExplored":false},{"Vari":{},"Taustavari":{},"Merkki":".","X":62,"Y":24,"IsTransparent":false,"IsWalkable":false,"IsInFov":true,"IsExplored":false},{"Vari":{},"Taustavari":{},"Merkki":".","X":63,"Y":24,"IsTransparent":false,"IsWalkable":false,"IsInFov":true,"IsExplored":false},{"Vari":{},"Taustavari":{},"Merkki":".","X":64,"Y":24,"IsTransparent":false,"IsWalkable":false,"IsInFov":true,"IsExplored":false},{"Vari":{},"Taustavari":{},"Merkki":".","X":65,"Y":24,"IsTransparent":false,"IsWalkable":false,"IsInFov":true,"IsExplored":false},{"Vari":{},"Taustavari":{},"Merkki":".","X":66,"Y":24,"IsTransparent":false,"IsWalkable":false,"IsInFov":true,"IsExplored":false},{"Vari":{},"Taustavari":{},"Merkki":".","X":67,"Y":24,"IsTransparent":false,"IsWalkable":false,"IsInFov":true,"IsExplored":false},{"Vari":{},"Taustavari":{},"Merkki":".","X":68,"Y":24,"IsTransparent":false,"IsWalkable":false,"IsInFov":true,"IsExplored":false},{"Vari":{},"Taustavari":{},"Merkki":".","X":69,"Y":24,"IsTransparent":false,"IsWalkable":false,"IsInFov":true,"IsExplored":false},{"Vari":{},"Taustavari":{},"Merkki":".","X":70,"Y":24,"IsTransparent":false,"IsWalkable":false,"IsInFov":true,"IsExplored":false},{"Vari":{},"Taustavari":{},"Merkki":".","X":71,"Y":24,"IsTransparent":false,"IsWalkable":false,"IsInFov":true,"IsExplored":false},{"Vari":{},"Taustavari":{},"Merkki":".","X":49,"Y":25,"IsTransparent":false,"IsWalkable":false,"IsInFov":true,"IsExplored":false},{"Vari":{},"Taustavari":{},"Merkki":".","X":50,"Y":25,"IsTransparent":false,"IsWalkable":false,"IsInFov":true,"IsExplored":false},{"Vari":{},"Taustavari":{},"Merkki":".","X":51,"Y":25,"IsTransparent":false,"IsWalkable":false,"IsInFov":true,"IsExplored":false},{"Vari":{},"Taustavari":{},"Merkki":".","X":52,"Y":25,"IsTransparent":false,"IsWalkable":false,"IsInFov":true,"IsExplored":false},{"Vari":{},"Taustavari":{},"Merkki":".","X":53,"Y":25,"IsTransparent":false,"IsWalkable":false,"IsInFov":true,"IsExplored":false},{"Vari":{},"Taustavari":{},"Merkki":".","X":54,"Y":25,"IsTransparent":false,"IsWalkable":false,"IsInFov":true,"IsExplored":false},{"Vari":{},"Taustavari":{},"Merkki":".","X":55,"Y":25,"IsTransparent":false,"IsWalkable":false,"IsInFov":true,"IsExplored":false},{"Vari":{},"Taustavari":{},"Merkki":".","X":56,"Y":25,"IsTransparent":false,"IsWalkable":false,"IsInFov":true,"IsExplored":false},{"Vari":{},"Taustavari":{},"Merkki":".","X":57,"Y":25,"IsTransparent":false,"IsWalkable":false,"IsInFov":true,"IsExplored":false},{"Vari":{},"Taustavari":{},"Merkki":".","X":58,"Y":25,"IsTransparent":false,"IsWalkable":false,"IsInFov":true,"IsExplored":false},{"Vari":{},"Taustavari":{},"Merkki":".","X":59,"Y":25,"IsTransparent":false,"IsWalkable":false,"IsInFov":true,"IsExplored":false},{"Vari":{},"Taustavari":{},"Merkki":".","X":60,"Y":25,"IsTransparent":false,"IsWalkable":false,"IsInFov":true,"IsExplored":false},{"Vari":{},"Taustavari":{},"Merkki":".","X":61,"Y":25,"IsTransparent":false,"IsWalkable":false,"IsInFov":true,"IsExplored":false},{"Vari":{},"Taustavari":{},"Merkki":".","X":62,"Y":25,"IsTransparent":false,"IsWalkable":false,"IsInFov":true,"IsExplored":false},{"Vari":{},"Taustavari":{},"Merkki":".","X":63,"Y":25,"IsTransparent":false,"IsWalkable":false,"IsInFov":true,"IsExplored":false},{"Vari":{},"Taustavari":{},"Merkki":".","X":64,"Y":25,"IsTransparent":false,"IsWalkable":false,"IsInFov":true,"IsExplored":false},{"Vari":{},"Taustavari":{},"Merkki":".","X":65,"Y":25,"IsTransparent":false,"IsWalkable":false,"IsInFov":true,"IsExplored":false},{"Vari":{},"Taustavari":{},"Merkki":".","X":66,"Y":25,"IsTransparent":false,"IsWalkable":false,"IsInFov":true,"IsExplored":false},{"Vari":{},"Taustavari":{},"Merkki":".","X":67,"Y":25,"IsTransparent":false,"IsWalkable":false,"IsInFov":true,"IsExplored":false},{"Vari":{},"Taustavari":{},"Merkki":".","X":68,"Y":25,"IsTransparent":false,"IsWalkable":false,"IsInFov":true,"IsExplored":false},{"Vari":{},"Taustavari":{},"Merkki":".","X":69,"Y":25,"IsTransparent":false,"IsWalkable":false,"IsInFov":true,"IsExplored":false},{"Vari":{},"Taustavari":{},"Merkki":".","X":70,"Y":25,"IsTransparent":false,"IsWalkable":false,"IsInFov":true,"IsExplored":false},{"Vari":{},"Taustavari":{},"Merkki":".","X":71,"Y":25,"IsTransparent":false,"IsWalkable":false,"IsInFov":true,"IsExplored":false},{"Vari":{},"Taustavari":{},"Merkki":".","X":49,"Y":26,"IsTransparent":false,"IsWalkable":false,"IsInFov":true,"IsExplored":false},{"Vari":{},"Taustavari":{},"Merkki":".","X":50,"Y":26,"IsTransparent":false,"IsWalkable":false,"IsInFov":true,"IsExplored":false},{"Vari":{},"Taustavari":{},"Merkki":".","X":51,"Y":26,"IsTransparent":false,"IsWalkable":false,"IsInFov":true,"IsExplored":false},{"Vari":{},"Taustavari":{},"Merkki":".","X":52,"Y":26,"IsTransparent":false,"IsWalkable":false,"IsInFov":true,"IsExplored":false},{"Vari":{},"Taustavari":{},"Merkki":".","X":53,"Y":26,"IsTransparent":false,"IsWalkable":false,"IsInFov":true,"IsExplored":false},{"Vari":{},"Taustavari":{},"Merkki":".","X":54,"Y":26,"IsTransparent":false,"IsWalkable":false,"IsInFov":true,"IsExplored":false},{"Vari":{},"Taustavari":{},"Merkki":".","X":55,"Y":26,"IsTransparent":false,"IsWalkable":false,"IsInFov":true,"IsExplored":false},{"Vari":{},"Taustavari":{},"Merkki":".","X":56,"Y":26,"IsTransparent":false,"IsWalkable":false,"IsInFov":true,"IsExplored":false},{"Vari":{},"Taustavari":{},"Merkki":".","X":57,"Y":26,"IsTransparent":false,"IsWalkable":false,"IsInFov":true,"IsExplored":false},{"Vari":{},"Taustavari":{},"Merkki":".","X":58,"Y":26,"IsTransparent":false,"IsWalkable":false,"IsInFov":true,"IsExplored":false},{"Vari":{},"Taustavari":{},"Merkki":".","X":59,"Y":26,"IsTransparent":false,"IsWalkable":false,"IsInFov":true,"IsExplored":false},{"Vari":{},"Taustavari":{},"Merkki":".","X":60,"Y":26,"IsTransparent":false,"IsWalkable":false,"IsInFov":true,"IsExplored":false},{"Vari":{},"Taustavari":{},"Merkki":".","X":61,"Y":26,"IsTransparent":false,"IsWalkable":false,"IsInFov":true,"IsExplored":false},{"Vari":{},"Taustavari":{},"Merkki":".","X":62,"Y":26,"IsTransparent":false,"IsWalkable":false,"IsInFov":true,"IsExplored":false},{"Vari":{},"Taustavari":{},"Merkki":".","X":63,"Y":26,"IsTransparent":false,"IsWalkable":false,"IsInFov":true,"IsExplored":false},{"Vari":{},"Taustavari":{},"Merkki":".","X":64,"Y":26,"IsTransparent":false,"IsWalkable":false,"IsInFov":true,"IsExplored":false},{"Vari":{},"Taustavari":{},"Merkki":".","X":65,"Y":26,"IsTransparent":false,"IsWalkable":false,"IsInFov":true,"IsExplored":false},{"Vari":{},"Taustavari":{},"Merkki":".","X":66,"Y":26,"IsTransparent":false,"IsWalkable":false,"IsInFov":true,"IsExplored":false},{"Vari":{},"Taustavari":{},"Merkki":".","X":67,"Y":26,"IsTransparent":false,"IsWalkable":false,"IsInFov":true,"IsExplored":false},{"Vari":{},"Taustavari":{},"Merkki":".","X":68,"Y":26,"IsTransparent":false,"IsWalkable":false,"IsInFov":true,"IsExplored":false},{"Vari":{},"Taustavari":{},"Merkki":".","X":69,"Y":26,"IsTransparent":false,"IsWalkable":false,"IsInFov":true,"IsExplored":false},{"Vari":{},"Taustavari":{},"Merkki":".","X":70,"Y":26,"IsTransparent":false,"IsWalkable":false,"IsInFov":true,"IsExplored":false},{"Vari":{},"Taustavari":{},"Merkki":".","X":71,"Y":26,"IsTransparent":false,"IsWalkable":false,"IsInFov":true,"IsExplored":false},{"Vari":{},"Taustavari":{},"Merkki":".","X":49,"Y":27,"IsTransparent":false,"IsWalkable":false,"IsInFov":true,"IsExplored":false},{"Vari":{},"Taustavari":{},"Merkki":".","X":50,"Y":27,"IsTransparent":false,"IsWalkable":false,"IsInFov":true,"IsExplored":false},{"Vari":{},"Taustavari":{},"Merkki":".","X":51,"Y":27,"IsTransparent":false,"IsWalkable":false,"IsInFov":true,"IsExplored":false},{"Vari":{},"Taustavari":{},"Merkki":".","X":52,"Y":27,"IsTransparent":false,"IsWalkable":false,"IsInFov":true,"IsExplored":false},{"Vari":{},"Taustavari":{},"Merkki":".","X":53,"Y":27,"IsTransparent":false,"IsWalkable":false,"IsInFov":true,"IsExplored":false},{"Vari":{},"Taustavari":{},"Merkki":".","X":54,"Y":27,"IsTransparent":false,"IsWalkable":false,"IsInFov":true,"IsExplored":false},{"Vari":{},"Taustavari":{},"Merkki":".","X":55,"Y":27,"IsTransparent":false,"IsWalkable":false,"IsInFov":true,"IsExplored":false},{"Vari":{},"Taustavari":{},"Merkki":".","X":56,"Y":27,"IsTransparent":false,"IsWalkable":false,"IsInFov":true,"IsExplored":false},{"Vari":{},"Taustavari":{},"Merkki":".","X":57,"Y":27,"IsTransparent":false,"IsWalkable":false,"IsInFov":true,"IsExplored":false},{"Vari":{},"Taustavari":{},"Merkki":".","X":58,"Y":27,"IsTransparent":false,"IsWalkable":false,"IsInFov":true,"IsExplored":false},{"Vari":{},"Taustavari":{},"Merkki":".","X":59,"Y":27,"IsTransparent":false,"IsWalkable":false,"IsInFov":true,"IsExplored":false},{"Vari":{},"Taustavari":{},"Merkki":".","X":60,"Y":27,"IsTransparent":false,"IsWalkable":false,"IsInFov":true,"IsExplored":false},{"Vari":{},"Taustavari":{},"Merkki":".","X":61,"Y":27,"IsTransparent":false,"IsWalkable":false,"IsInFov":true,"IsExplored":false},{"Vari":{},"Taustavari":{},"Merkki":".","X":62,"Y":27,"IsTransparent":false,"IsWalkable":false,"IsInFov":true,"IsExplored":false},{"Vari":{},"Taustavari":{},"Merkki":".","X":63,"Y":27,"IsTransparent":false,"IsWalkable":false,"IsInFov":true,"IsExplored":false},{"Vari":{},"Taustavari":{},"Merkki":".","X":64,"Y":27,"IsTransparent":false,"IsWalkable":false,"IsInFov":true,"IsExplored":false},{"Vari":{},"Taustavari":{},"Merkki":".","X":65,"Y":27,"IsTransparent":false,"IsWalkable":false,"IsInFov":true,"IsExplored":false},{"Vari":{},"Taustavari":{},"Merkki":".","X":66,"Y":27,"IsTransparent":false,"IsWalkable":false,"IsInFov":true,"IsExplored":false},{"Vari":{},"Taustavari":{},"Merkki":".","X":67,"Y":27,"IsTransparent":false,"IsWalkable":false,"IsInFov":true,"IsExplored":false},{"Vari":{},"Taustavari":{},"Merkki":".","X":68,"Y":27,"IsTransparent":false,"IsWalkable":false,"IsInFov":true,"IsExplored":false},{"Vari":{},"Taustavari":{},"Merkki":".","X":69,"Y":27,"IsTransparent":false,"IsWalkable":false,"IsInFov":true,"IsExplored":false},{"Vari":{},"Taustavari":{},"Merkki":".","X":70,"Y":27,"IsTransparent":false,"IsWalkable":false,"IsInFov":true,"IsExplored":false},{"Vari":{},"Taustavari":{},"Merkki":".","X":71,"Y":27,"IsTransparent":false,"IsWalkable":false,"IsInFov":true,"IsExplored":false},{"Vari":{},"Taustavari":{},"Merkki":".","X":49,"Y":28,"IsTransparent":false,"IsWalkable":false,"IsInFov":true,"IsExplored":false},{"Vari":{},"Taustavari":{},"Merkki":".","X":50,"Y":28,"IsTransparent":false,"IsWalkable":false,"IsInFov":true,"IsExplored":false},{"Vari":{},"Taustavari":{},"Merkki":".","X":51,"Y":28,"IsTransparent":false,"IsWalkable":false,"IsInFov":true,"IsExplored":false},{"Vari":{},"Taustavari":{},"Merkki":".","X":52,"Y":28,"IsTransparent":false,"IsWalkable":false,"IsInFov":true,"IsExplored":false},{"Vari":{},"Taustavari":{},"Merkki":".","X":53,"Y":28,"IsTransparent":false,"IsWalkable":false,"IsInFov":true,"IsExplored":false},{"Vari":{},"Taustavari":{},"Merkki":".","X":54,"Y":28,"IsTransparent":false,"IsWalkable":false,"IsInFov":true,"IsExplored":false},{"Vari":{},"Taustavari":{},"Merkki":".","X":55,"Y":28,"IsTransparent":false,"IsWalkable":false,"IsInFov":true,"IsExplored":false},{"Vari":{},"Taustavari":{},"Merkki":".","X":56,"Y":28,"IsTransparent":false,"IsWalkable":false,"IsInFov":true,"IsExplored":false},{"Vari":{},"Taustavari":{},"Merkki":".","X":57,"Y":28,"IsTransparent":false,"IsWalkable":false,"IsInFov":true,"IsExplored":false},{"Vari":{},"Taustavari":{},"Merkki":".","X":58,"Y":28,"IsTransparent":false,"IsWalkable":false,"IsInFov":true,"IsExplored":false},{"Vari":{},"Taustavari":{},"Merkki":".","X":59,"Y":28,"IsTransparent":false,"IsWalkable":false,"IsInFov":true,"IsExplored":false},{"Vari":{},"Taustavari":{},"Merkki":".","X":60,"Y":28,"IsTransparent":false,"IsWalkable":false,"IsInFov":true,"IsExplored":false},{"Vari":{},"Taustavari":{},"Merkki":".","X":61,"Y":28,"IsTransparent":false,"IsWalkable":false,"IsInFov":true,"IsExplored":false},{"Vari":{},"Taustavari":{},"Merkki":".","X":62,"Y":28,"IsTransparent":false,"IsWalkable":false,"IsInFov":true,"IsExplored":false},{"Vari":{},"Taustavari":{},"Merkki":".","X":63,"Y":28,"IsTransparent":false,"IsWalkable":false,"IsInFov":true,"IsExplored":false},{"Vari":{},"Taustavari":{},"Merkki":".","X":64,"Y":28,"IsTransparent":false,"IsWalkable":false,"IsInFov":true,"IsExplored":false},{"Vari":{},"Taustavari":{},"Merkki":".","X":65,"Y":28,"IsTransparent":false,"IsWalkable":false,"IsInFov":true,"IsExplored":false},{"Vari":{},"Taustavari":{},"Merkki":".","X":66,"Y":28,"IsTransparent":false,"IsWalkable":false,"IsInFov":true,"IsExplored":false},{"Vari":{},"Taustavari":{},"Merkki":".","X":67,"Y":28,"IsTransparent":false,"IsWalkable":false,"IsInFov":true,"IsExplored":false},{"Vari":{},"Taustavari":{},"Merkki":".","X":68,"Y":28,"IsTransparent":false,"IsWalkable":false,"IsInFov":true,"IsExplored":false},{"Vari":{},"Taustavari":{},"Merkki":".","X":69,"Y":28,"IsTransparent":false,"IsWalkable":false,"IsInFov":true,"IsExplored":false},{"Vari":{},"Taustavari":{},"Merkki":".","X":70,"Y":28,"IsTransparent":false,"IsWalkable":false,"IsInFov":true,"IsExplored":false},{"Vari":{},"Taustavari":{},"Merkki":".","X":71,"Y":28,"IsTransparent":false,"IsWalkable":false,"IsInFov":true,"IsExplored":false},{"Vari":{},"Taustavari":{},"Merkki":".","X":49,"Y":29,"IsTransparent":false,"IsWalkable":false,"IsInFov":true,"IsExplored":false},{"Vari":{},"Taustavari":{},"Merkki":".","X":50,"Y":29,"IsTransparent":false,"IsWalkable":false,"IsInFov":true,"IsExplored":false},{"Vari":{},"Taustavari":{},"Merkki":".","X":51,"Y":29,"IsTransparent":false,"IsWalkable":false,"IsInFov":true,"IsExplored":false},{"Vari":{},"Taustavari":{},"Merkki":".","X":52,"Y":29,"IsTransparent":false,"IsWalkable":false,"IsInFov":true,"IsExplored":false},{"Vari":{},"Taustavari":{},"Merkki":".","X":53,"Y":29,"IsTransparent":false,"IsWalkable":false,"IsInFov":true,"IsExplored":false},{"Vari":{},"Taustavari":{},"Merkki":".","X":54,"Y":29,"IsTransparent":false,"IsWalkable":false,"IsInFov":true,"IsExplored":false},{"Vari":{},"Taustavari":{},"Merkki":".","X":55,"Y":29,"IsTransparent":false,"IsWalkable":false,"IsInFov":true,"IsExplored":false},{"Vari":{},"Taustavari":{},"Merkki":".","X":56,"Y":29,"IsTransparent":false,"IsWalkable":false,"IsInFov":true,"IsExplored":false},{"Vari":{},"Taustavari":{},"Merkki":".","X":57,"Y":29,"IsTransparent":false,"IsWalkable":false,"IsInFov":true,"IsExplored":false},{"Vari":{},"Taustavari":{},"Merkki":".","X":58,"Y":29,"IsTransparent":false,"IsWalkable":false,"IsInFov":true,"IsExplored":false},{"Vari":{},"Taustavari":{},"Merkki":".","X":59,"Y":29,"IsTransparent":false,"IsWalkable":false,"IsInFov":true,"IsExplored":false},{"Vari":{},"Taustavari":{},"Merkki":".","X":60,"Y":29,"IsTransparent":false,"IsWalkable":false,"IsInFov":true,"IsExplored":false},{"Vari":{},"Taustavari":{},"Merkki":".","X":61,"Y":29,"IsTransparent":false,"IsWalkable":false,"IsInFov":true,"IsExplored":false},{"Vari":{},"Taustavari":{},"Merkki":".","X":62,"Y":29,"IsTransparent":false,"IsWalkable":false,"IsInFov":true,"IsExplored":false},{"Vari":{},"Taustavari":{},"Merkki":".","X":63,"Y":29,"IsTransparent":false,"IsWalkable":false,"IsInFov":true,"IsExplored":false},{"Vari":{},"Taustavari":{},"Merkki":".","X":64,"Y":29,"IsTransparent":false,"IsWalkable":false,"IsInFov":true,"IsExplored":false},{"Vari":{},"Taustavari":{},"Merkki":".","X":65,"Y":29,"IsTransparent":false,"IsWalkable":false,"IsInFov":true,"IsExplored":false},{"Vari":{},"Taustavari":{},"Merkki":".","X":66,"Y":29,"IsTransparent":false,"IsWalkable":false,"IsInFov":true,"IsExplored":false},{"Vari":{},"Taustavari":{},"Merkki":".","X":67,"Y":29,"IsTransparent":false,"IsWalkable":false,"IsInFov":true,"IsExplored":false},{"Vari":{},"Taustavari":{},"Merkki":".","X":68,"Y":29,"IsTransparent":false,"IsWalkable":false,"IsInFov":true,"IsExplored":false},{"Vari":{},"Taustavari":{},"Merkki":".","X":69,"Y":29,"IsTransparent":false,"IsWalkable":false,"IsInFov":true,"IsExplored":false},{"Vari":{},"Taustavari":{},"Merkki":".","X":70,"Y":29,"IsTransparent":false,"IsWalkable":false,"IsInFov":true,"IsExplored":false},{"Vari":{},"Taustavari":{},"Merkki":".","X":71,"Y":29,"IsTransparent":false,"IsWalkable":false,"IsInFov":true,"IsExplored":false},{"Vari":{},"Taustavari":{},"Merkki":".","X":49,"Y":30,"IsTransparent":false,"IsWalkable":false,"IsInFov":true,"IsExplored":false},{"Vari":{},"Taustavari":{},"Merkki":".","X":50,"Y":30,"IsTransparent":false,"IsWalkable":false,"IsInFov":true,"IsExplored":false},{"Vari":{},"Taustavari":{},"Merkki":".","X":51,"Y":30,"IsTransparent":false,"IsWalkable":false,"IsInFov":true,"IsExplored":false},{"Vari":{},"Taustavari":{},"Merkki":".","X":52,"Y":30,"IsTransparent":false,"IsWalkable":false,"IsInFov":true,"IsExplored":false},{"Vari":{},"Taustavari":{},"Merkki":".","X":53,"Y":30,"IsTransparent":false,"IsWalkable":false,"IsInFov":true,"IsExplored":false},{"Vari":{},"Taustavari":{},"Merkki":".","X":54,"Y":30,"IsTransparent":false,"IsWalkable":false,"IsInFov":true,"IsExplored":false},{"Vari":{},"Taustavari":{},"Merkki":".","X":55,"Y":30,"IsTransparent":false,"IsWalkable":false,"IsInFov":true,"IsExplored":false},{"Vari":{},"Taustavari":{},"Merkki":".","X":56,"Y":30,"IsTransparent":false,"IsWalkable":false,"IsInFov":true,"IsExplored":false},{"Vari":{},"Taustavari":{},"Merkki":".","X":57,"Y":30,"IsTransparent":false,"IsWalkable":false,"IsInFov":true,"IsExplored":false},{"Vari":{},"Taustavari":{},"Merkki":".","X":58,"Y":30,"IsTransparent":false,"IsWalkable":false,"IsInFov":true,"IsExplored":false},{"Vari":{},"Taustavari":{},"Merkki":".","X":59,"Y":30,"IsTransparent":false,"IsWalkable":false,"IsInFov":true,"IsExplored":false},{"Vari":{},"Taustavari":{},"Merkki":".","X":60,"Y":30,"IsTransparent":false,"IsWalkable":false,"IsInFov":true,"IsExplored":false},{"Vari":{},"Taustavari":{},"Merkki":".","X":61,"Y":30,"IsTransparent":false,"IsWalkable":false,"IsInFov":true,"IsExplored":false},{"Vari":{},"Taustavari":{},"Merkki":".","X":62,"Y":30,"IsTransparent":false,"IsWalkable":false,"IsInFov":true,"IsExplored":false},{"Vari":{},"Taustavari":{},"Merkki":".","X":63,"Y":30,"IsTransparent":false,"IsWalkable":false,"IsInFov":true,"IsExplored":false},{"Vari":{},"Taustavari":{},"Merkki":".","X":64,"Y":30,"IsTransparent":false,"IsWalkable":false,"IsInFov":true,"IsExplored":false},{"Vari":{},"Taustavari":{},"Merkki":".","X":65,"Y":30,"IsTransparent":false,"IsWalkable":false,"IsInFov":true,"IsExplored":false},{"Vari":{},"Taustavari":{},"Merkki":".","X":66,"Y":30,"IsTransparent":false,"IsWalkable":false,"IsInFov":true,"IsExplored":false},{"Vari":{},"Taustavari":{},"Merkki":".","X":67,"Y":30,"IsTransparent":false,"IsWalkable":false,"IsInFov":true,"IsExplored":false},{"Vari":{},"Taustavari":{},"Merkki":".","X":68,"Y":30,"IsTransparent":false,"IsWalkable":false,"IsInFov":true,"IsExplored":false},{"Vari":{},"Taustavari":{},"Merkki":".","X":69,"Y":30,"IsTransparent":false,"IsWalkable":false,"IsInFov":true,"IsExplored":false},{"Vari":{},"Taustavari":{},"Merkki":".","X":70,"Y":30,"IsTransparent":false,"IsWalkable":false,"IsInFov":true,"IsExplored":false},{"Vari":{},"Taustavari":{},"Merkki":".","X":71,"Y":30,"IsTransparent":false,"IsWalkable":false,"IsInFov":true,"IsExplored":false},{"Vari":{},"Taustavari":{},"Merkki":".","X":49,"Y":31,"IsTransparent":false,"IsWalkable":false,"IsInFov":true,"IsExplored":false},{"Vari":{},"Taustavari":{},"Merkki":".","X":50,"Y":31,"IsTransparent":false,"IsWalkable":false,"IsInFov":true,"IsExplored":false},{"Vari":{},"Taustavari":{},"Merkki":".","X":51,"Y":31,"IsTransparent":false,"IsWalkable":false,"IsInFov":true,"IsExplored":false},{"Vari":{},"Taustavari":{},"Merkki":".","X":52,"Y":31,"IsTransparent":false,"IsWalkable":false,"IsInFov":true,"IsExplored":false},{"Vari":{},"Taustavari":{},"Merkki":".","X":53,"Y":31,"IsTransparent":false,"IsWalkable":false,"IsInFov":true,"IsExplored":false},{"Vari":{},"Taustavari":{},"Merkki":".","X":54,"Y":31,"IsTransparent":false,"IsWalkable":false,"IsInFov":true,"IsExplored":false},{"Vari":{},"Taustavari":{},"Merkki":".","X":55,"Y":31,"IsTransparent":false,"IsWalkable":false,"IsInFov":true,"IsExplored":false},{"Vari":{},"Taustavari":{},"Merkki":".","X":56,"Y":31,"IsTransparent":false,"IsWalkable":false,"IsInFov":true,"IsExplored":false},{"Vari":{},"Taustavari":{},"Merkki":".","X":57,"Y":31,"IsTransparent":false,"IsWalkable":false,"IsInFov":true,"IsExplored":false},{"Vari":{},"Taustavari":{},"Merkki":".","X":58,"Y":31,"IsTransparent":false,"IsWalkable":false,"IsInFov":true,"IsExplored":false},{"Vari":{},"Taustavari":{},"Merkki":".","X":59,"Y":31,"IsTransparent":false,"IsWalkable":false,"IsInFov":true,"IsExplored":false},{"Vari":{},"Taustavari":{},"Merkki":".","X":60,"Y":31,"IsTransparent":false,"IsWalkable":false,"IsInFov":true,"IsExplored":false},{"Vari":{},"Taustavari":{},"Merkki":".","X":61,"Y":31,"IsTransparent":false,"IsWalkable":false,"IsInFov":true,"IsExplored":false},{"Vari":{},"Taustavari":{},"Merkki":".","X":62,"Y":31,"IsTransparent":false,"IsWalkable":false,"IsInFov":true,"IsExplored":false},{"Vari":{},"Taustavari":{},"Merkki":".","X":63,"Y":31,"IsTransparent":false,"IsWalkable":false,"IsInFov":true,"IsExplored":false},{"Vari":{},"Taustavari":{},"Merkki":".","X":64,"Y":31,"IsTransparent":false,"IsWalkable":false,"IsInFov":true,"IsExplored":false},{"Vari":{},"Taustavari":{},"Merkki":".","X":65,"Y":31,"IsTransparent":false,"IsWalkable":false,"IsInFov":true,"IsExplored":false},{"Vari":{},"Taustavari":{},"Merkki":".","X":66,"Y":31,"IsTransparent":false,"IsWalkable":false,"IsInFov":true,"IsExplored":false},{"Vari":{},"Taustavari":{},"Merkki":".","X":67,"Y":31,"IsTransparent":false,"IsWalkable":false,"IsInFov":true,"IsExplored":false},{"Vari":{},"Taustavari":{},"Merkki":".","X":68,"Y":31,"IsTransparent":false,"IsWalkable":false,"IsInFov":true,"IsExplored":false},{"Vari":{},"Taustavari":{},"Merkki":".","X":69,"Y":31,"IsTransparent":false,"IsWalkable":false,"IsInFov":true,"IsExplored":false},{"Vari":{},"Taustavari":{},"Merkki":".","X":70,"Y":31,"IsTransparent":false,"IsWalkable":false,"IsInFov":true,"IsExplored":false},{"Vari":{},"Taustavari":{},"Merkki":".","X":71,"Y":31,"IsTransparent":false,"IsWalkable":false,"IsInFov":true,"IsExplored":false},{"Vari":{},"Taustavari":{},"Merkki":".","X":49,"Y":32,"IsTransparent":false,"IsWalkable":false,"IsInFov":true,"IsExplored":false},{"Vari":{},"Taustavari":{},"Merkki":".","X":50,"Y":32,"IsTransparent":false,"IsWalkable":false,"IsInFov":true,"IsExplored":false},{"Vari":{},"Taustavari":{},"Merkki":".","X":51,"Y":32,"IsTransparent":false,"IsWalkable":false,"IsInFov":true,"IsExplored":false},{"Vari":{},"Taustavari":{},"Merkki":".","X":52,"Y":32,"IsTransparent":false,"IsWalkable":false,"IsInFov":true,"IsExplored":false},{"Vari":{},"Taustavari":{},"Merkki":".","X":53,"Y":32,"IsTransparent":false,"IsWalkable":false,"IsInFov":true,"IsExplored":false},{"Vari":{},"Taustavari":{},"Merkki":".","X":54,"Y":32,"IsTransparent":false,"IsWalkable":false,"IsInFov":true,"IsExplored":false},{"Vari":{},"Taustavari":{},"Merkki":".","X":55,"Y":32,"IsTransparent":false,"IsWalkable":false,"IsInFov":true,"IsExplored":false},{"Vari":{},"Taustavari":{},"Merkki":".","X":56,"Y":32,"IsTransparent":false,"IsWalkable":false,"IsInFov":true,"IsExplored":false},{"Vari":{},"Taustavari":{},"Merkki":".","X":57,"Y":32,"IsTransparent":false,"IsWalkable":false,"IsInFov":true,"IsExplored":false},{"Vari":{},"Taustavari":{},"Merkki":".","X":58,"Y":32,"IsTransparent":false,"IsWalkable":false,"IsInFov":true,"IsExplored":false},{"Vari":{},"Taustavari":{},"Merkki":".","X":59,"Y":32,"IsTransparent":false,"IsWalkable":false,"IsInFov":true,"IsExplored":false},{"Vari":{},"Taustavari":{},"Merkki":".","X":60,"Y":32,"IsTransparent":false,"IsWalkable":false,"IsInFov":true,"IsExplored":false},{"Vari":{},"Taustavari":{},"Merkki":".","X":61,"Y":32,"IsTransparent":false,"IsWalkable":false,"IsInFov":true,"IsExplored":false},{"Vari":{},"Taustavari":{},"Merkki":".","X":62,"Y":32,"IsTransparent":false,"IsWalkable":false,"IsInFov":true,"IsExplored":false},{"Vari":{},"Taustavari":{},"Merkki":".","X":63,"Y":32,"IsTransparent":false,"IsWalkable":false,"IsInFov":true,"IsExplored":false},{"Vari":{},"Taustavari":{},"Merkki":".","X":64,"Y":32,"IsTransparent":false,"IsWalkable":false,"IsInFov":true,"IsExplored":false},{"Vari":{},"Taustavari":{},"Merkki":".","X":65,"Y":32,"IsTransparent":false,"IsWalkable":false,"IsInFov":true,"IsExplored":false},{"Vari":{},"Taustavari":{},"Merkki":".","X":66,"Y":32,"IsTransparent":false,"IsWalkable":false,"IsInFov":true,"IsExplored":false},{"Vari":{},"Taustavari":{},"Merkki":".","X":67,"Y":32,"IsTransparent":false,"IsWalkable":false,"IsInFov":true,"IsExplored":false},{"Vari":{},"Taustavari":{},"Merkki":".","X":68,"Y":32,"IsTransparent":false,"IsWalkable":false,"IsInFov":true,"IsExplored":false},{"Vari":{},"Taustavari":{},"Merkki":".","X":69,"Y":32,"IsTransparent":false,"IsWalkable":false,"IsInFov":true,"IsExplored":false},{"Vari":{},"Taustavari":{},"Merkki":".","X":70,"Y":32,"IsTransparent":false,"IsWalkable":false,"IsInFov":true,"IsExplored":false},{"Vari":{},"Taustavari":{},"Merkki":".","X":71,"Y":32,"IsTransparent":false,"IsWalkable":false,"IsInFov":true,"IsExplored":false},{"Vari":{},"Taustavari":{},"Merkki":".","X":49,"Y":33,"IsTransparent":false,"IsWalkable":false,"IsInFov":true,"IsExplored":false},{"Vari":{},"Taustavari":{},"Merkki":".","X":50,"Y":33,"IsTransparent":false,"IsWalkable":false,"IsInFov":true,"IsExplored":false},{"Vari":{},"Taustavari":{},"Merkki":".","X":51,"Y":33,"IsTransparent":false,"IsWalkable":false,"IsInFov":true,"IsExplored":false},{"Vari":{},"Taustavari":{},"Merkki":".","X":52,"Y":33,"IsTransparent":false,"IsWalkable":false,"IsInFov":true,"IsExplored":false},{"Vari":{},"Taustavari":{},"Merkki":".","X":53,"Y":33,"IsTransparent":false,"IsWalkable":false,"IsInFov":true,"IsExplored":false},{"Vari":{},"Taustavari":{},"Merkki":".","X":54,"Y":33,"IsTransparent":false,"IsWalkable":false,"IsInFov":true,"IsExplored":false},{"Vari":{},"Taustavari":{},"Merkki":".","X":55,"Y":33,"IsTransparent":false,"IsWalkable":false,"IsInFov":true,"IsExplored":false},{"Vari":{},"Taustavari":{},"Merkki":".","X":56,"Y":33,"IsTransparent":false,"IsWalkable":false,"IsInFov":true,"IsExplored":false},{"Vari":{},"Taustavari":{},"Merkki":".","X":57,"Y":33,"IsTransparent":false,"IsWalkable":false,"IsInFov":true,"IsExplored":false},{"Vari":{},"Taustavari":{},"Merkki":".","X":58,"Y":33,"IsTransparent":false,"IsWalkable":false,"IsInFov":true,"IsExplored":false},{"Vari":{},"Taustavari":{},"Merkki":".","X":59,"Y":33,"IsTransparent":false,"IsWalkable":false,"IsInFov":true,"IsExplored":false},{"Vari":{},"Taustavari":{},"Merkki":".","X":60,"Y":33,"IsTransparent":false,"IsWalkable":false,"IsInFov":true,"IsExplored":false},{"Vari":{},"Taustavari":{},"Merkki":".","X":61,"Y":33,"IsTransparent":false,"IsWalkable":false,"IsInFov":true,"IsExplored":false},{"Vari":{},"Taustavari":{},"Merkki":".","X":62,"Y":33,"IsTransparent":false,"IsWalkable":false,"IsInFov":true,"IsExplored":false},{"Vari":{},"Taustavari":{},"Merkki":".","X":63,"Y":33,"IsTransparent":false,"IsWalkable":false,"IsInFov":true,"IsExplored":false},{"Vari":{},"Taustavari":{},"Merkki":".","X":64,"Y":33,"IsTransparent":false,"IsWalkable":false,"IsInFov":true,"IsExplored":false},{"Vari":{},"Taustavari":{},"Merkki":".","X":65,"Y":33,"IsTransparent":false,"IsWalkable":false,"IsInFov":true,"IsExplored":false},{"Vari":{},"Taustavari":{},"Merkki":".","X":66,"Y":33,"IsTransparent":false,"IsWalkable":false,"IsInFov":true,"IsExplored":false},{"Vari":{},"Taustavari":{},"Merkki":".","X":67,"Y":33,"IsTransparent":false,"IsWalkable":false,"IsInFov":true,"IsExplored":false},{"Vari":{},"Taustavari":{},"Merkki":".","X":68,"Y":33,"IsTransparent":false,"IsWalkable":false,"IsInFov":true,"IsExplored":false},{"Vari":{},"Taustavari":{},"Merkki":".","X":69,"Y":33,"IsTransparent":false,"IsWalkable":false,"IsInFov":true,"IsExplored":false},{"Vari":{},"Taustavari":{},"Merkki":".","X":70,"Y":33,"IsTransparent":false,"IsWalkable":false,"IsInFov":true,"IsExplored":false},{"Vari":{},"Taustavari":{},"Merkki":".","X":71,"Y":33,"IsTransparent":false,"IsWalkable":false,"IsInFov":true,"IsExplored":false},{"Vari":{},"Taustavari":{},"Merkki":".","X":49,"Y":34,"IsTransparent":false,"IsWalkable":false,"IsInFov":true,"IsExplored":false},{"Vari":{},"Taustavari":{},"Merkki":".","X":50,"Y":34,"IsTransparent":false,"IsWalkable":false,"IsInFov":true,"IsExplored":false},{"Vari":{},"Taustavari":{},"Merkki":".","X":51,"Y":34,"IsTransparent":false,"IsWalkable":false,"IsInFov":true,"IsExplored":false},{"Vari":{},"Taustavari":{},"Merkki":".","X":52,"Y":34,"IsTransparent":false,"IsWalkable":false,"IsInFov":true,"IsExplored":false},{"Vari":{},"Taustavari":{},"Merkki":".","X":53,"Y":34,"IsTransparent":false,"IsWalkable":false,"IsInFov":true,"IsExplored":false},{"Vari":{},"Taustavari":{},"Merkki":".","X":54,"Y":34,"IsTransparent":false,"IsWalkable":false,"IsInFov":true,"IsExplored":false},{"Vari":{},"Taustavari":{},"Merkki":".","X":55,"Y":34,"IsTransparent":false,"IsWalkable":false,"IsInFov":true,"IsExplored":false},{"Vari":{},"Taustavari":{},"Merkki":".","X":56,"Y":34,"IsTransparent":false,"IsWalkable":false,"IsInFov":true,"IsExplored":false},{"Vari":{},"Taustavari":{},"Merkki":".","X":57,"Y":34,"IsTransparent":false,"IsWalkable":false,"IsInFov":true,"IsExplored":false},{"Vari":{},"Taustavari":{},"Merkki":".","X":58,"Y":34,"IsTransparent":false,"IsWalkable":false,"IsInFov":true,"IsExplored":false},{"Vari":{},"Taustavari":{},"Merkki":".","X":59,"Y":34,"IsTransparent":false,"IsWalkable":false,"IsInFov":true,"IsExplored":false},{"Vari":{},"Taustavari":{},"Merkki":".","X":60,"Y":34,"IsTransparent":false,"IsWalkable":false,"IsInFov":true,"IsExplored":false},{"Vari":{},"Taustavari":{},"Merkki":".","X":61,"Y":34,"IsTransparent":false,"IsWalkable":false,"IsInFov":true,"IsExplored":false},{"Vari":{},"Taustavari":{},"Merkki":".","X":62,"Y":34,"IsTransparent":false,"IsWalkable":false,"IsInFov":true,"IsExplored":false},{"Vari":{},"Taustavari":{},"Merkki":".","X":63,"Y":34,"IsTransparent":false,"IsWalkable":false,"IsInFov":true,"IsExplored":false},{"Vari":{},"Taustavari":{},"Merkki":".","X":64,"Y":34,"IsTransparent":false,"IsWalkable":false,"IsInFov":true,"IsExplored":false},{"Vari":{},"Taustavari":{},"Merkki":".","X":65,"Y":34,"IsTransparent":false,"IsWalkable":false,"IsInFov":true,"IsExplored":false},{"Vari":{},"Taustavari":{},"Merkki":".","X":66,"Y":34,"IsTransparent":false,"IsWalkable":false,"IsInFov":true,"IsExplored":false},{"Vari":{},"Taustavari":{},"Merkki":".","X":67,"Y":34,"IsTransparent":false,"IsWalkable":false,"IsInFov":true,"IsExplored":false},{"Vari":{},"Taustavari":{},"Merkki":".","X":68,"Y":34,"IsTransparent":false,"IsWalkable":false,"IsInFov":true,"IsExplored":false},{"Vari":{},"Taustavari":{},"Merkki":".","X":69,"Y":34,"IsTransparent":false,"IsWalkable":false,"IsInFov":true,"IsExplored":false},{"Vari":{},"Taustavari":{},"Merkki":".","X":70,"Y":34,"IsTransparent":false,"IsWalkable":false,"IsInFov":true,"IsExplored":false},{"Vari":{},"Taustavari":{},"Merkki":".","X":71,"Y":34,"IsTransparent":false,"IsWalkable":false,"IsInFov":true,"IsExplored":false},{"Vari":{},"Taustavari":{},"Merkki":".","X":49,"Y":35,"IsTransparent":false,"IsWalkable":false,"IsInFov":true,"IsExplored":false},{"Vari":{},"Taustavari":{},"Merkki":".","X":50,"Y":35,"IsTransparent":false,"IsWalkable":false,"IsInFov":true,"IsExplored":false},{"Vari":{},"Taustavari":{},"Merkki":".","X":51,"Y":35,"IsTransparent":false,"IsWalkable":false,"IsInFov":true,"IsExplored":false},{"Vari":{},"Taustavari":{},"Merkki":".","X":52,"Y":35,"IsTransparent":false,"IsWalkable":false,"IsInFov":true,"IsExplored":false},{"Vari":{},"Taustavari":{},"Merkki":".","X":53,"Y":35,"IsTransparent":false,"IsWalkable":false,"IsInFov":true,"IsExplored":false},{"Vari":{},"Taustavari":{},"Merkki":".","X":54,"Y":35,"IsTransparent":false,"IsWalkable":false,"IsInFov":true,"IsExplored":false},{"Vari":{},"Taustavari":{},"Merkki":".","X":55,"Y":35,"IsTransparent":false,"IsWalkable":false,"IsInFov":true,"IsExplored":false},{"Vari":{},"Taustavari":{},"Merkki":".","X":56,"Y":35,"IsTransparent":false,"IsWalkable":false,"IsInFov":true,"IsExplored":false},{"Vari":{},"Taustavari":{},"Merkki":".","X":57,"Y":35,"IsTransparent":false,"IsWalkable":false,"IsInFov":true,"IsExplored":false},{"Vari":{},"Taustavari":{},"Merkki":".","X":58,"Y":35,"IsTransparent":false,"IsWalkable":false,"IsInFov":true,"IsExplored":false},{"Vari":{},"Taustavari":{},"Merkki":".","X":59,"Y":35,"IsTransparent":false,"IsWalkable":false,"IsInFov":true,"IsExplored":false},{"Vari":{},"Taustavari":{},"Merkki":".","X":60,"Y":35,"IsTransparent":false,"IsWalkable":false,"IsInFov":true,"IsExplored":false},{"Vari":{},"Taustavari":{},"Merkki":".","X":61,"Y":35,"IsTransparent":false,"IsWalkable":false,"IsInFov":true,"IsExplored":false},{"Vari":{},"Taustavari":{},"Merkki":".","X":62,"Y":35,"IsTransparent":false,"IsWalkable":false,"IsInFov":true,"IsExplored":false},{"Vari":{},"Taustavari":{},"Merkki":".","X":63,"Y":35,"IsTransparent":false,"IsWalkable":false,"IsInFov":true,"IsExplored":false},{"Vari":{},"Taustavari":{},"Merkki":".","X":64,"Y":35,"IsTransparent":false,"IsWalkable":false,"IsInFov":true,"IsExplored":false},{"Vari":{},"Taustavari":{},"Merkki":".","X":65,"Y":35,"IsTransparent":false,"IsWalkable":false,"IsInFov":true,"IsExplored":false},{"Vari":{},"Taustavari":{},"Merkki":".","X":66,"Y":35,"IsTransparent":false,"IsWalkable":false,"IsInFov":true,"IsExplored":false},{"Vari":{},"Taustavari":{},"Merkki":".","X":67,"Y":35,"IsTransparent":false,"IsWalkable":false,"IsInFov":true,"IsExplored":false},{"Vari":{},"Taustavari":{},"Merkki":".","X":68,"Y":35,"IsTransparent":false,"IsWalkable":false,"IsInFov":true,"IsExplored":false},{"Vari":{},"Taustavari":{},"Merkki":".","X":69,"Y":35,"IsTransparent":false,"IsWalkable":false,"IsInFov":true,"IsExplored":false},{"Vari":{},"Taustavari":{},"Merkki":".","X":70,"Y":35,"IsTransparent":false,"IsWalkable":false,"IsInFov":true,"IsExplored":false},{"Vari":{},"Taustavari":{},"Merkki":".","X":71,"Y":35,"IsTransparent":false,"IsWalkable":false,"IsInFov":true,"IsExplored":false},{"Vari":{},"Taustavari":{},"Merkki":".","X":49,"Y":36,"IsTransparent":false,"IsWalkable":false,"IsInFov":true,"IsExplored":false},{"Vari":{},"Taustavari":{},"Merkki":".","X":50,"Y":36,"IsTransparent":false,"IsWalkable":false,"IsInFov":true,"IsExplored":false},{"Vari":{},"Taustavari":{},"Merkki":".","X":51,"Y":36,"IsTransparent":false,"IsWalkable":false,"IsInFov":true,"IsExplored":false},{"Vari":{},"Taustavari":{},"Merkki":".","X":52,"Y":36,"IsTransparent":false,"IsWalkable":false,"IsInFov":true,"IsExplored":false},{"Vari":{},"Taustavari":{},"Merkki":".","X":53,"Y":36,"IsTransparent":false,"IsWalkable":false,"IsInFov":true,"IsExplored":false},{"Vari":{},"Taustavari":{},"Merkki":".","X":54,"Y":36,"IsTransparent":false,"IsWalkable":false,"IsInFov":true,"IsExplored":false},{"Vari":{},"Taustavari":{},"Merkki":".","X":55,"Y":36,"IsTransparent":false,"IsWalkable":false,"IsInFov":true,"IsExplored":false},{"Vari":{},"Taustavari":{},"Merkki":".","X":56,"Y":36,"IsTransparent":false,"IsWalkable":false,"IsInFov":true,"IsExplored":false},{"Vari":{},"Taustavari":{},"Merkki":".","X":57,"Y":36,"IsTransparent":false,"IsWalkable":false,"IsInFov":true,"IsExplored":false},{"Vari":{},"Taustavari":{},"Merkki":".","X":58,"Y":36,"IsTransparent":false,"IsWalkable":false,"IsInFov":true,"IsExplored":false},{"Vari":{},"Taustavari":{},"Merkki":".","X":59,"Y":36,"IsTransparent":false,"IsWalkable":false,"IsInFov":true,"IsExplored":false},{"Vari":{},"Taustavari":{},"Merkki":".","X":60,"Y":36,"IsTransparent":false,"IsWalkable":false,"IsInFov":true,"IsExplored":false},{"Vari":{},"Taustavari":{},"Merkki":".","X":61,"Y":36,"IsTransparent":false,"IsWalkable":false,"IsInFov":true,"IsExplored":false},{"Vari":{},"Taustavari":{},"Merkki":".","X":62,"Y":36,"IsTransparent":false,"IsWalkable":false,"IsInFov":true,"IsExplored":false},{"Vari":{},"Taustavari":{},"Merkki":".","X":63,"Y":36,"IsTransparent":false,"IsWalkable":false,"IsInFov":true,"IsExplored":false},{"Vari":{},"Taustavari":{},"Merkki":".","X":64,"Y":36,"IsTransparent":false,"IsWalkable":false,"IsInFov":true,"IsExplored":false},{"Vari":{},"Taustavari":{},"Merkki":".","X":65,"Y":36,"IsTransparent":false,"IsWalkable":false,"IsInFov":true,"IsExplored":false},{"Vari":{},"Taustavari":{},"Merkki":".","X":66,"Y":36,"IsTransparent":false,"IsWalkable":false,"IsInFov":true,"IsExplored":false},{"Vari":{},"Taustavari":{},"Merkki":".","X":67,"Y":36,"IsTransparent":false,"IsWalkable":false,"IsInFov":true,"IsExplored":false},{"Vari":{},"Taustavari":{},"Merkki":".","X":68,"Y":36,"IsTransparent":false,"IsWalkable":false,"IsInFov":true,"IsExplored":false},{"Vari":{},"Taustavari":{},"Merkki":".","X":69,"Y":36,"IsTransparent":false,"IsWalkable":false,"IsInFov":true,"IsExplored":false},{"Vari":{},"Taustavari":{},"Merkki":".","X":70,"Y":36,"IsTransparent":false,"IsWalkable":false,"IsInFov":true,"IsExplored":false},{"Vari":{},"Taustavari":{},"Merkki":".","X":71,"Y":36,"IsTransparent":false,"IsWalkable":false,"IsInFov":true,"IsExplored":false},{"Vari":{},"Taustavari":{},"Merkki":".","X":49,"Y":37,"IsTransparent":false,"IsWalkable":false,"IsInFov":true,"IsExplored":false},{"Vari":{},"Taustavari":{},"Merkki":".","X":50,"Y":37,"IsTransparent":false,"IsWalkable":false,"IsInFov":true,"IsExplored":false},{"Vari":{},"Taustavari":{},"Merkki":".","X":51,"Y":37,"IsTransparent":false,"IsWalkable":false,"IsInFov":true,"IsExplored":false},{"Vari":{},"Taustavari":{},"Merkki":".","X":52,"Y":37,"IsTransparent":false,"IsWalkable":false,"IsInFov":true,"IsExplored":false},{"Vari":{},"Taustavari":{},"Merkki":".","X":53,"Y":37,"IsTransparent":false,"IsWalkable":false,"IsInFov":true,"IsExplored":false},{"Vari":{},"Taustavari":{},"Merkki":".","X":54,"Y":37,"IsTransparent":false,"IsWalkable":false,"IsInFov":true,"IsExplored":false},{"Vari":{},"Taustavari":{},"Merkki":".","X":55,"Y":37,"IsTransparent":false,"IsWalkable":false,"IsInFov":true,"IsExplored":false},{"Vari":{},"Taustavari":{},"Merkki":".","X":56,"Y":37,"IsTransparent":false,"IsWalkable":false,"IsInFov":true,"IsExplored":false},{"Vari":{},"Taustavari":{},"Merkki":".","X":57,"Y":37,"IsTransparent":false,"IsWalkable":false,"IsInFov":true,"IsExplored":false},{"Vari":{},"Taustavari":{},"Merkki":".","X":58,"Y":37,"IsTransparent":false,"IsWalkable":false,"IsInFov":true,"IsExplored":false},{"Vari":{},"Taustavari":{},"Merkki":".","X":59,"Y":37,"IsTransparent":false,"IsWalkable":false,"IsInFov":true,"IsExplored":false},{"Vari":{},"Taustavari":{},"Merkki":".","X":60,"Y":37,"IsTransparent":false,"IsWalkable":false,"IsInFov":true,"IsExplored":false},{"Vari":{},"Taustavari":{},"Merkki":".","X":61,"Y":37,"IsTransparent":false,"IsWalkable":false,"IsInFov":true,"IsExplored":false},{"Vari":{},"Taustavari":{},"Merkki":".","X":62,"Y":37,"IsTransparent":false,"IsWalkable":false,"IsInFov":true,"IsExplored":false},{"Vari":{},"Taustavari":{},"Merkki":".","X":63,"Y":37,"IsTransparent":false,"IsWalkable":false,"IsInFov":true,"IsExplored":false},{"Vari":{},"Taustavari":{},"Merkki":".","X":64,"Y":37,"IsTransparent":false,"IsWalkable":false,"IsInFov":true,"IsExplored":false},{"Vari":{},"Taustavari":{},"Merkki":".","X":65,"Y":37,"IsTransparent":false,"IsWalkable":false,"IsInFov":true,"IsExplored":false},{"Vari":{},"Taustavari":{},"Merkki":".","X":66,"Y":37,"IsTransparent":false,"IsWalkable":false,"IsInFov":true,"IsExplored":false},{"Vari":{},"Taustavari":{},"Merkki":".","X":67,"Y":37,"IsTransparent":false,"IsWalkable":false,"IsInFov":true,"IsExplored":false},{"Vari":{},"Taustavari":{},"Merkki":".","X":68,"Y":37,"IsTransparent":false,"IsWalkable":false,"IsInFov":true,"IsExplored":false},{"Vari":{},"Taustavari":{},"Merkki":".","X":69,"Y":37,"IsTransparent":false,"IsWalkable":false,"IsInFov":true,"IsExplored":false},{"Vari":{},"Taustavari":{},"Merkki":".","X":70,"Y":37,"IsTransparent":false,"IsWalkable":false,"IsInFov":true,"IsExplored":false},{"Vari":{},"Taustavari":{},"Merkki":".","X":71,"Y":37,"IsTransparent":false,"IsWalkable":false,"IsInFov":true,"IsExplored":false},{"Vari":{},"Taustavari":{},"Merkki":".","X":49,"Y":38,"IsTransparent":false,"IsWalkable":false,"IsInFov":true,"IsExplored":false},{"Vari":{},"Taustavari":{},"Merkki":".","X":50,"Y":38,"IsTransparent":false,"IsWalkable":false,"IsInFov":true,"IsExplored":false},{"Vari":{},"Taustavari":{},"Merkki":".","X":51,"Y":38,"IsTransparent":false,"IsWalkable":false,"IsInFov":true,"IsExplored":false},{"Vari":{},"Taustavari":{},"Merkki":".","X":52,"Y":38,"IsTransparent":false,"IsWalkable":false,"IsInFov":true,"IsExplored":false},{"Vari":{},"Taustavari":{},"Merkki":".","X":53,"Y":38,"IsTransparent":false,"IsWalkable":false,"IsInFov":true,"IsExplored":false},{"Vari":{},"Taustavari":{},"Merkki":".","X":54,"Y":38,"IsTransparent":false,"IsWalkable":false,"IsInFov":true,"IsExplored":false},{"Vari":{},"Taustavari":{},"Merkki":".","X":55,"Y":38,"IsTransparent":false,"IsWalkable":false,"IsInFov":true,"IsExplored":false},{"Vari":{},"Taustavari":{},"Merkki":".","X":56,"Y":38,"IsTransparent":false,"IsWalkable":false,"IsInFov":true,"IsExplored":false},{"Vari":{},"Taustavari":{},"Merkki":".","X":57,"Y":38,"IsTransparent":false,"IsWalkable":false,"IsInFov":true,"IsExplored":false},{"Vari":{},"Taustavari":{},"Merkki":".","X":58,"Y":38,"IsTransparent":false,"IsWalkable":false,"IsInFov":true,"IsExplored":false},{"Vari":{},"Taustavari":{},"Merkki":".","X":59,"Y":38,"IsTransparent":false,"IsWalkable":false,"IsInFov":true,"IsExplored":false},{"Vari":{},"Taustavari":{},"Merkki":".","X":60,"Y":38,"IsTransparent":false,"IsWalkable":false,"IsInFov":true,"IsExplored":false},{"Vari":{},"Taustavari":{},"Merkki":".","X":61,"Y":38,"IsTransparent":false,"IsWalkable":false,"IsInFov":true,"IsExplored":false},{"Vari":{},"Taustavari":{},"Merkki":".","X":62,"Y":38,"IsTransparent":false,"IsWalkable":false,"IsInFov":true,"IsExplored":false},{"Vari":{},"Taustavari":{},"Merkki":".","X":63,"Y":38,"IsTransparent":false,"IsWalkable":false,"IsInFov":true,"IsExplored":false},{"Vari":{},"Taustavari":{},"Merkki":".","X":64,"Y":38,"IsTransparent":false,"IsWalkable":false,"IsInFov":true,"IsExplored":false},{"Vari":{},"Taustavari":{},"Merkki":".","X":65,"Y":38,"IsTransparent":false,"IsWalkable":false,"IsInFov":true,"IsExplored":false},{"Vari":{},"Taustavari":{},"Merkki":".","X":66,"Y":38,"IsTransparent":false,"IsWalkable":false,"IsInFov":true,"IsExplored":false},{"Vari":{},"Taustavari":{},"Merkki":".","X":67,"Y":38,"IsTransparent":false,"IsWalkable":false,"IsInFov":true,"IsExplored":false},{"Vari":{},"Taustavari":{},"Merkki":".","X":68,"Y":38,"IsTransparent":false,"IsWalkable":false,"IsInFov":true,"IsExplored":false},{"Vari":{},"Taustavari":{},"Merkki":".","X":69,"Y":38,"IsTransparent":false,"IsWalkable":false,"IsInFov":true,"IsExplored":false},{"Vari":{},"Taustavari":{},"Merkki":".","X":70,"Y":38,"IsTransparent":false,"IsWalkable":false,"IsInFov":true,"IsExplored":false},{"Vari":{},"Taustavari":{},"Merkki":".","X":71,"Y":38,"IsTransparent":false,"IsWalkable":false,"IsInFov":true,"IsExplored":false},{"Vari":{},"Taustavari":{},"Merkki":".","X":49,"Y":39,"IsTransparent":false,"IsWalkable":false,"IsInFov":true,"IsExplored":false},{"Vari":{},"Taustavari":{},"Merkki":".","X":50,"Y":39,"IsTransparent":false,"IsWalkable":false,"IsInFov":true,"IsExplored":false},{"Vari":{},"Taustavari":{},"Merkki":".","X":51,"Y":39,"IsTransparent":false,"IsWalkable":false,"IsInFov":true,"IsExplored":false},{"Vari":{},"Taustavari":{},"Merkki":".","X":52,"Y":39,"IsTransparent":false,"IsWalkable":false,"IsInFov":true,"IsExplored":false},{"Vari":{},"Taustavari":{},"Merkki":".","X":53,"Y":39,"IsTransparent":false,"IsWalkable":false,"IsInFov":true,"IsExplored":false},{"Vari":{},"Taustavari":{},"Merkki":".","X":54,"Y":39,"IsTransparent":false,"IsWalkable":false,"IsInFov":true,"IsExplored":false},{"Vari":{},"Taustavari":{},"Merkki":".","X":55,"Y":39,"IsTransparent":false,"IsWalkable":false,"IsInFov":true,"IsExplored":false},{"Vari":{},"Taustavari":{},"Merkki":".","X":56,"Y":39,"IsTransparent":false,"IsWalkable":false,"IsInFov":true,"IsExplored":false},{"Vari":{},"Taustavari":{},"Merkki":".","X":57,"Y":39,"IsTransparent":false,"IsWalkable":false,"IsInFov":true,"IsExplored":false},{"Vari":{},"Taustavari":{},"Merkki":".","X":58,"Y":39,"IsTransparent":false,"IsWalkable":false,"IsInFov":true,"IsExplored":false},{"Vari":{},"Taustavari":{},"Merkki":".","X":59,"Y":39,"IsTransparent":false,"IsWalkable":false,"IsInFov":true,"IsExplored":false},{"Vari":{},"Taustavari":{},"Merkki":".","X":60,"Y":39,"IsTransparent":false,"IsWalkable":false,"IsInFov":true,"IsExplored":false},{"Vari":{},"Taustavari":{},"Merkki":".","X":61,"Y":39,"IsTransparent":false,"IsWalkable":false,"IsInFov":true,"IsExplored":false},{"Vari":{},"Taustavari":{},"Merkki":".","X":62,"Y":39,"IsTransparent":false,"IsWalkable":false,"IsInFov":true,"IsExplored":false},{"Vari":{},"Taustavari":{},"Merkki":".","X":63,"Y":39,"IsTransparent":false,"IsWalkable":false,"IsInFov":true,"IsExplored":false},{"Vari":{},"Taustavari":{},"Merkki":".","X":64,"Y":39,"IsTransparent":false,"IsWalkable":false,"IsInFov":true,"IsExplored":false},{"Vari":{},"Taustavari":{},"Merkki":".","X":65,"Y":39,"IsTransparent":false,"IsWalkable":false,"IsInFov":true,"IsExplored":false},{"Vari":{},"Taustavari":{},"Merkki":".","X":66,"Y":39,"IsTransparent":false,"IsWalkable":false,"IsInFov":true,"IsExplored":false},{"Vari":{},"Taustavari":{},"Merkki":".","X":67,"Y":39,"IsTransparent":false,"IsWalkable":false,"IsInFov":true,"IsExplored":false},{"Vari":{},"Taustavari":{},"Merkki":".","X":68,"Y":39,"IsTransparent":false,"IsWalkable":false,"IsInFov":true,"IsExplored":false},{"Vari":{},"Taustavari":{},"Merkki":".","X":69,"Y":39,"IsTransparent":false,"IsWalkable":false,"IsInFov":true,"IsExplored":false},{"Vari":{},"Taustavari":{},"Merkki":".","X":70,"Y":39,"IsTransparent":false,"IsWalkable":false,"IsInFov":true,"IsExplored":false},{"Vari":{},"Taustavari":{},"Merkki":".","X":71,"Y":39,"IsTransparent":false,"IsWalkable":false,"IsInFov":true,"IsExplored":false},{"Vari":{},"Taustavari":{},"Merkki":".","X":49,"Y":40,"IsTransparent":false,"IsWalkable":false,"IsInFov":true,"IsExplored":false},{"Vari":{},"Taustavari":{},"Merkki":".","X":50,"Y":40,"IsTransparent":false,"IsWalkable":false,"IsInFov":true,"IsExplored":false},{"Vari":{},"Taustavari":{},"Merkki":".","X":51,"Y":40,"IsTransparent":false,"IsWalkable":false,"IsInFov":true,"IsExplored":false},{"Vari":{},"Taustavari":{},"Merkki":".","X":52,"Y":40,"IsTransparent":false,"IsWalkable":false,"IsInFov":true,"IsExplored":false},{"Vari":{},"Taustavari":{},"Merkki":".","X":53,"Y":40,"IsTransparent":false,"IsWalkable":false,"IsInFov":true,"IsExplored":false},{"Vari":{},"Taustavari":{},"Merkki":".","X":54,"Y":40,"IsTransparent":false,"IsWalkable":false,"IsInFov":true,"IsExplored":false},{"Vari":{},"Taustavari":{},"Merkki":".","X":55,"Y":40,"IsTransparent":false,"IsWalkable":false,"IsInFov":true,"IsExplored":false},{"Vari":{},"Taustavari":{},"Merkki":".","X":56,"Y":40,"IsTransparent":false,"IsWalkable":false,"IsInFov":true,"IsExplored":false},{"Vari":{},"Taustavari":{},"Merkki":".","X":57,"Y":40,"IsTransparent":false,"IsWalkable":false,"IsInFov":true,"IsExplored":false},{"Vari":{},"Taustavari":{},"Merkki":".","X":58,"Y":40,"IsTransparent":false,"IsWalkable":false,"IsInFov":true,"IsExplored":false},{"Vari":{},"Taustavari":{},"Merkki":".","X":59,"Y":40,"IsTransparent":false,"IsWalkable":false,"IsInFov":true,"IsExplored":false},{"Vari":{},"Taustavari":{},"Merkki":".","X":60,"Y":40,"IsTransparent":false,"IsWalkable":false,"IsInFov":true,"IsExplored":false},{"Vari":{},"Taustavari":{},"Merkki":".","X":61,"Y":40,"IsTransparent":false,"IsWalkable":false,"IsInFov":true,"IsExplored":false},{"Vari":{},"Taustavari":{},"Merkki":".","X":62,"Y":40,"IsTransparent":false,"IsWalkable":false,"IsInFov":true,"IsExplored":false},{"Vari":{},"Taustavari":{},"Merkki":".","X":63,"Y":40,"IsTransparent":false,"IsWalkable":false,"IsInFov":true,"IsExplored":false},{"Vari":{},"Taustavari":{},"Merkki":".","X":64,"Y":40,"IsTransparent":false,"IsWalkable":false,"IsInFov":true,"IsExplored":false},{"Vari":{},"Taustavari":{},"Merkki":".","X":65,"Y":40,"IsTransparent":false,"IsWalkable":false,"IsInFov":true,"IsExplored":false},{"Vari":{},"Taustavari":{},"Merkki":".","X":66,"Y":40,"IsTransparent":false,"IsWalkable":false,"IsInFov":true,"IsExplored":false},{"Vari":{},"Taustavari":{},"Merkki":".","X":67,"Y":40,"IsTransparent":false,"IsWalkable":false,"IsInFov":true,"IsExplored":false},{"Vari":{},"Taustavari":{},"Merkki":".","X":68,"Y":40,"IsTransparent":false,"IsWalkable":false,"IsInFov":true,"IsExplored":false},{"Vari":{},"Taustavari":{},"Merkki":".","X":69,"Y":40,"IsTransparent":false,"IsWalkable":false,"IsInFov":true,"IsExplored":false},{"Vari":{},"Taustavari":{},"Merkki":".","X":70,"Y":40,"IsTransparent":false,"IsWalkable":false,"IsInFov":true,"IsExplored":false},{"Vari":{},"Taustavari":{},"Merkki":".","X":71,"Y":40,"IsTransparent":false,"IsWalkable":false,"IsInFov":true,"IsExplored":false},{"Vari":{},"Taustavari":{},"Merkki":".","X":49,"Y":41,"IsTransparent":false,"IsWalkable":false,"IsInFov":true,"IsExplored":false},{"Vari":{},"Taustavari":{},"Merkki":".","X":50,"Y":41,"IsTransparent":false,"IsWalkable":false,"IsInFov":true,"IsExplored":false},{"Vari":{},"Taustavari":{},"Merkki":".","X":51,"Y":41,"IsTransparent":false,"IsWalkable":false,"IsInFov":true,"IsExplored":false},{"Vari":{},"Taustavari":{},"Merkki":".","X":52,"Y":41,"IsTransparent":false,"IsWalkable":false,"IsInFov":true,"IsExplored":false},{"Vari":{},"Taustavari":{},"Merkki":".","X":53,"Y":41,"IsTransparent":false,"IsWalkable":false,"IsInFov":true,"IsExplored":false},{"Vari":{},"Taustavari":{},"Merkki":".","X":54,"Y":41,"IsTransparent":false,"IsWalkable":false,"IsInFov":true,"IsExplored":false},{"Vari":{},"Taustavari":{},"Merkki":".","X":55,"Y":41,"IsTransparent":false,"IsWalkable":false,"IsInFov":true,"IsExplored":false},{"Vari":{},"Taustavari":{},"Merkki":".","X":56,"Y":41,"IsTransparent":false,"IsWalkable":false,"IsInFov":true,"IsExplored":false},{"Vari":{},"Taustavari":{},"Merkki":".","X":57,"Y":41,"IsTransparent":false,"IsWalkable":false,"IsInFov":true,"IsExplored":false},{"Vari":{},"Taustavari":{},"Merkki":".","X":58,"Y":41,"IsTransparent":false,"IsWalkable":false,"IsInFov":true,"IsExplored":false},{"Vari":{},"Taustavari":{},"Merkki":".","X":59,"Y":41,"IsTransparent":false,"IsWalkable":false,"IsInFov":true,"IsExplored":false},{"Vari":{},"Taustavari":{},"Merkki":".","X":60,"Y":41,"IsTransparent":false,"IsWalkable":false,"IsInFov":true,"IsExplored":false},{"Vari":{},"Taustavari":{},"Merkki":".","X":61,"Y":41,"IsTransparent":false,"IsWalkable":false,"IsInFov":true,"IsExplored":false},{"Vari":{},"Taustavari":{},"Merkki":".","X":62,"Y":41,"IsTransparent":false,"IsWalkable":false,"IsInFov":true,"IsExplored":false},{"Vari":{},"Taustavari":{},"Merkki":".","X":63,"Y":41,"IsTransparent":false,"IsWalkable":false,"IsInFov":true,"IsExplored":false},{"Vari":{},"Taustavari":{},"Merkki":".","X":64,"Y":41,"IsTransparent":false,"IsWalkable":false,"IsInFov":true,"IsExplored":false},{"Vari":{},"Taustavari":{},"Merkki":".","X":65,"Y":41,"IsTransparent":false,"IsWalkable":false,"IsInFov":true,"IsExplored":false},{"Vari":{},"Taustavari":{},"Merkki":".","X":66,"Y":41,"IsTransparent":false,"IsWalkable":false,"IsInFov":true,"IsExplored":false},{"Vari":{},"Taustavari":{},"Merkki":".","X":67,"Y":41,"IsTransparent":false,"IsWalkable":false,"IsInFov":true,"IsExplored":false},{"Vari":{},"Taustavari":{},"Merkki":".","X":68,"Y":41,"IsTransparent":false,"IsWalkable":false,"IsInFov":true,"IsExplored":false},{"Vari":{},"Taustavari":{},"Merkki":".","X":69,"Y":41,"IsTransparent":false,"IsWalkable":false,"IsInFov":true,"IsExplored":false},{"Vari":{},"Taustavari":{},"Merkki":".","X":70,"Y":41,"IsTransparent":false,"IsWalkable":false,"IsInFov":true,"IsExplored":false},{"Vari":{},"Taustavari":{},"Merkki":".","X":71,"Y":41,"IsTransparent":false,"IsWalkable":false,"IsInFov":true,"IsExplored":false},{"Vari":{},"Taustavari":{},"Merkki":".","X":49,"Y":42,"IsTransparent":false,"IsWalkable":false,"IsInFov":true,"IsExplored":false},{"Vari":{},"Taustavari":{},"Merkki":".","X":50,"Y":42,"IsTransparent":false,"IsWalkable":false,"IsInFov":true,"IsExplored":false},{"Vari":{},"Taustavari":{},"Merkki":".","X":51,"Y":42,"IsTransparent":false,"IsWalkable":false,"IsInFov":true,"IsExplored":false},{"Vari":{},"Taustavari":{},"Merkki":".","X":52,"Y":42,"IsTransparent":false,"IsWalkable":false,"IsInFov":true,"IsExplored":false},{"Vari":{},"Taustavari":{},"Merkki":".","X":53,"Y":42,"IsTransparent":false,"IsWalkable":false,"IsInFov":true,"IsExplored":false},{"Vari":{},"Taustavari":{},"Merkki":".","X":54,"Y":42,"IsTransparent":false,"IsWalkable":false,"IsInFov":true,"IsExplored":false},{"Vari":{},"Taustavari":{},"Merkki":".","X":55,"Y":42,"IsTransparent":false,"IsWalkable":false,"IsInFov":true,"IsExplored":false},{"Vari":{},"Taustavari":{},"Merkki":".","X":56,"Y":42,"IsTransparent":false,"IsWalkable":false,"IsInFov":true,"IsExplored":false},{"Vari":{},"Taustavari":{},"Merkki":".","X":57,"Y":42,"IsTransparent":false,"IsWalkable":false,"IsInFov":true,"IsExplored":false},{"Vari":{},"Taustavari":{},"Merkki":".","X":58,"Y":42,"IsTransparent":false,"IsWalkable":false,"IsInFov":true,"IsExplored":false},{"Vari":{},"Taustavari":{},"Merkki":".","X":59,"Y":42,"IsTransparent":false,"IsWalkable":false,"IsInFov":true,"IsExplored":false},{"Vari":{},"Taustavari":{},"Merkki":".","X":60,"Y":42,"IsTransparent":false,"IsWalkable":false,"IsInFov":true,"IsExplored":false},{"Vari":{},"Taustavari":{},"Merkki":".","X":61,"Y":42,"IsTransparent":false,"IsWalkable":false,"IsInFov":true,"IsExplored":false},{"Vari":{},"Taustavari":{},"Merkki":".","X":62,"Y":42,"IsTransparent":false,"IsWalkable":false,"IsInFov":true,"IsExplored":false},{"Vari":{},"Taustavari":{},"Merkki":".","X":63,"Y":42,"IsTransparent":false,"IsWalkable":false,"IsInFov":true,"IsExplored":false},{"Vari":{},"Taustavari":{},"Merkki":".","X":64,"Y":42,"IsTransparent":false,"IsWalkable":false,"IsInFov":true,"IsExplored":false},{"Vari":{},"Taustavari":{},"Merkki":".","X":65,"Y":42,"IsTransparent":false,"IsWalkable":false,"IsInFov":true,"IsExplored":false},{"Vari":{},"Taustavari":{},"Merkki":".","X":66,"Y":42,"IsTransparent":false,"IsWalkable":false,"IsInFov":true,"IsExplored":false},{"Vari":{},"Taustavari":{},"Merkki":".","X":67,"Y":42,"IsTransparent":false,"IsWalkable":false,"IsInFov":true,"IsExplored":false},{"Vari":{},"Taustavari":{},"Merkki":".","X":68,"Y":42,"IsTransparent":false,"IsWalkable":false,"IsInFov":true,"IsExplored":false},{"Vari":{},"Taustavari":{},"Merkki":".","X":69,"Y":42,"IsTransparent":false,"IsWalkable":false,"IsInFov":true,"IsExplored":false},{"Vari":{},"Taustavari":{},"Merkki":".","X":70,"Y":42,"IsTransparent":false,"IsWalkable":false,"IsInFov":true,"IsExplored":false},{"Vari":{},"Taustavari":{},"Merkki":".","X":71,"Y":42,"IsTransparent":false,"IsWalkable":false,"IsInFov":true,"IsExplored":false},{"Vari":{},"Taustavari":{},"Merkki":".","X":49,"Y":43,"IsTransparent":false,"IsWalkable":false,"IsInFov":true,"IsExplored":false},{"Vari":{},"Taustavari":{},"Merkki":".","X":50,"Y":43,"IsTransparent":false,"IsWalkable":false,"IsInFov":true,"IsExplored":false},{"Vari":{},"Taustavari":{},"Merkki":".","X":51,"Y":43,"IsTransparent":false,"IsWalkable":false,"IsInFov":true,"IsExplored":false},{"Vari":{},"Taustavari":{},"Merkki":".","X":52,"Y":43,"IsTransparent":false,"IsWalkable":false,"IsInFov":true,"IsExplored":false},{"Vari":{},"Taustavari":{},"Merkki":".","X":53,"Y":43,"IsTransparent":false,"IsWalkable":false,"IsInFov":true,"IsExplored":false},{"Vari":{},"Taustavari":{},"Merkki":".","X":54,"Y":43,"IsTransparent":false,"IsWalkable":false,"IsInFov":true,"IsExplored":false},{"Vari":{},"Taustavari":{},"Merkki":".","X":55,"Y":43,"IsTransparent":false,"IsWalkable":false,"IsInFov":true,"IsExplored":false},{"Vari":{},"Taustavari":{},"Merkki":".","X":56,"Y":43,"IsTransparent":false,"IsWalkable":false,"IsInFov":true,"IsExplored":false},{"Vari":{},"Taustavari":{},"Merkki":".","X":57,"Y":43,"IsTransparent":false,"IsWalkable":false,"IsInFov":true,"IsExplored":false},{"Vari":{},"Taustavari":{},"Merkki":".","X":58,"Y":43,"IsTransparent":false,"IsWalkable":false,"IsInFov":true,"IsExplored":false},{"Vari":{},"Taustavari":{},"Merkki":".","X":59,"Y":43,"IsTransparent":false,"IsWalkable":false,"IsInFov":true,"IsExplored":false},{"Vari":{},"Taustavari":{},"Merkki":".","X":60,"Y":43,"IsTransparent":false,"IsWalkable":false,"IsInFov":true,"IsExplored":false},{"Vari":{},"Taustavari":{},"Merkki":".","X":61,"Y":43,"IsTransparent":false,"IsWalkable":false,"IsInFov":true,"IsExplored":false},{"Vari":{},"Taustavari":{},"Merkki":".","X":62,"Y":43,"IsTransparent":false,"IsWalkable":false,"IsInFov":true,"IsExplored":false},{"Vari":{},"Taustavari":{},"Merkki":".","X":63,"Y":43,"IsTransparent":false,"IsWalkable":false,"IsInFov":true,"IsExplored":false},{"Vari":{},"Taustavari":{},"Merkki":".","X":64,"Y":43,"IsTransparent":false,"IsWalkable":false,"IsInFov":true,"IsExplored":false},{"Vari":{},"Taustavari":{},"Merkki":".","X":65,"Y":43,"IsTransparent":false,"IsWalkable":false,"IsInFov":true,"IsExplored":false},{"Vari":{},"Taustavari":{},"Merkki":".","X":66,"Y":43,"IsTransparent":false,"IsWalkable":false,"IsInFov":true,"IsExplored":false},{"Vari":{},"Taustavari":{},"Merkki":".","X":67,"Y":43,"IsTransparent":false,"IsWalkable":false,"IsInFov":true,"IsExplored":false},{"Vari":{},"Taustavari":{},"Merkki":".","X":68,"Y":43,"IsTransparent":false,"IsWalkable":false,"IsInFov":true,"IsExplored":false},{"Vari":{},"Taustavari":{},"Merkki":".","X":69,"Y":43,"IsTransparent":false,"IsWalkable":false,"IsInFov":true,"IsExplored":false},{"Vari":{},"Taustavari":{},"Merkki":".","X":70,"Y":43,"IsTransparent":false,"IsWalkable":false,"IsInFov":true,"IsExplored":false},{"Vari":{},"Taustavari":{},"Merkki":".","X":71,"Y":43,"IsTransparent":false,"IsWalkable":false,"IsInFov":true,"IsExplored":false}],"Width":120,"Height":64}
{"Varusteet":[null,null,null,null,null],"Nalka":100,"Alykkyys":1,"Taso":1,"Nimi":"Player","Nakoetaisyys":25,"Vari":{},"Merkki":"@","X":60,"Y":32,"Napparyys":1,"Voimakkuus":1,"Puolustus":1,"Elama":20,"Inventaario":[]}
